airontools/__init__.py
airontools/constructors/__init__.py
airontools/constructors/blocks.py
airontools/constructors/layers.py
airontools/constructors/models/__init__.py
airontools/constructors/models/model.py
airontools/constructors/models/supervised/__init__.py
airontools/constructors/models/supervised/feed_forward.py
airontools/constructors/models/supervised/image_classifier.py
airontools/constructors/models/unsupervised/__init__.py
airontools/constructors/models/unsupervised/ae.py
airontools/constructors/models/unsupervised/vae.py
airontools/constructors/utils.py
airontools/devices.py
airontools/interactors.py
airontools/on_the_fly/__init__.py
airontools/on_the_fly/hyper_design_dropout_rate.py
airontools/path_utils.py
airontools/preprocessing_utils.py
airontools/tensorboard_utils.py
airontools-0.1.68.dist-info/METADATA
airontools-0.1.68.dist-info/WHEEL
airontools-0.1.68.dist-info/licenses/LICENSE
airontools-0.1.68.dist-info/RECORD
