Metadata-Version: 2.4
Name: airontools
Version: 0.1.68
Summary: AIronTools (Beta) is a Python library that provides the user with deep learning tools built to work with tensorflow as a backend.
License: BSD
License-File: LICENSE
Author: Claudi
Requires-Python: >=3.11
Classifier: License :: OSI Approved :: BSD License
Classifier: License :: Other/Proprietary License
Classifier: Operating System :: OS Independent
Classifier: Programming Language :: Python :: 3
Classifier: Programming Language :: Python :: 3.11
Classifier: Programming Language :: Python :: 3.12
Classifier: Programming Language :: Python :: 3.13
Classifier: Programming Language :: Python :: 3.14
Requires-Dist: h5py (>=3.10.0,<4.0.0)
Requires-Dist: keras (>=3.13.0,<4.0.0)
Requires-Dist: scikit-learn (>=1.2.2,<2.0.0)
Requires-Dist: tensorflow (==2.18.1)
Project-URL: Repository, https://github.com/AtrejuArtax/airontools
